sphinxcontrib_slide-1.0.0-py3.10-nspkg.pth
sphinxcontrib/slide.py
sphinxcontrib_slide-1.0.0.dist-info/METADATA
sphinxcontrib_slide-1.0.0.dist-info/WHEEL
sphinxcontrib_slide-1.0.0.dist-info/namespace_packages.txt
sphinxcontrib_slide-1.0.0.dist-info/top_level.txt
sphinxcontrib_slide-1.0.0.dist-info/RECORD
